aliyunsdkvideorecog/__init__.py
aliyunsdkvideorecog/endpoint.py
aliyunsdkvideorecog/request/__init__.py
aliyunsdkvideorecog/request/v20200320/DetectVideoShotRequest.py
aliyunsdkvideorecog/request/v20200320/EvaluateVideoQualityRequest.py
aliyunsdkvideorecog/request/v20200320/GenerateVideoCoverRequest.py
aliyunsdkvideorecog/request/v20200320/GetAsyncJobResultRequest.py
aliyunsdkvideorecog/request/v20200320/RecognizeVideoCastCrewListRequest.py
aliyunsdkvideorecog/request/v20200320/SplitVideoPartsRequest.py
aliyunsdkvideorecog/request/v20200320/UnderstandVideoContentRequest.py
aliyunsdkvideorecog/request/v20200320/__init__.py
aliyun_python_sdk_videorecog-1.0.9.dist-info/LICENSE
aliyun_python_sdk_videorecog-1.0.9.dist-info/METADATA
aliyun_python_sdk_videorecog-1.0.9.dist-info/WHEEL
aliyun_python_sdk_videorecog-1.0.9.dist-info/top_level.txt
aliyun_python_sdk_videorecog-1.0.9.dist-info/RECORD
